{"devicePlatform":"","logFolder":"C:\\Users\\Dennis Gituto\\git\\VSMS-Test-Automation\\Reports\\Request Meeting\\Sign up\\20171205_121847","runData":{"hostName":"Dennis Gituto - DESKTOP-IA8CIQG","os":"Windows 10 64bit","katalonVersion":"5.1.0.1","browser":"Chrome 62.0.3202.94","hostAddress":"192.168.1.101","sessionId":"f196045b3a7221c796a7bd1c5c6ef639","seleniumVersion":"3.7.1","proxyInformation":"ProxyInformation{proxyOption\u003dNO_PROXY, proxyServerType\u003dHTTP, password\u003d, proxyServerAddress\u003d, proxyServerPort\u003d0}","platform":"Windows 10"},"type":"TEST_SUITE","name":"Sign up","id":"Test Suites/Request Meeting/Sign up","source":"","message":"Test Cases/Request A Meeting/Sign Up in Request Meeting","description":"Sign up in order to request a meeting","startTime":1512465529132,"endTime":1512465592827,"childRecords":[{"isOptional":false,"type":"TEST_CASE","name":"Test Cases/Request A Meeting/Sign Up in Request Meeting","id":"Test Cases/Request A Meeting/Sign Up in Request Meeting","source":"C:\\\\Users\\\\Dennis Gituto\\\\git\\\\VSMS-Test-AutomationTest Cases\\\\Request A Meeting\\\\Sign Up in Request Meeting.tc","message":"Test Cases/Request A Meeting/Sign Up in Request Meeting","description":"Sign Up in Request Meeting in Homepage","startTime":1512465529466,"endTime":1512465592769,"childRecords":[{"testStatus":{"stackTrace":"","statusValue":"INFO"},"type":"MESSAGE","name":"","message":"Evaluating variables for test case","startTime":1512465529631,"endTime":0,"childRecords":[],"interuppted":false},{"testStatus":{"stackTrace":"","statusValue":"INFO"},"type":"MESSAGE","name":"","message":"Variable \u0027var_title\u0027 is set to Mr","startTime":1512465529688,"endTime":0,"childRecords":[],"interuppted":false},{"testStatus":{"stackTrace":"","statusValue":"INFO"},"type":"MESSAGE","name":"","message":"Variable \u0027var_firstName\u0027 is set to Dennis","startTime":1512465529690,"endTime":0,"childRecords":[],"interuppted":false},{"testStatus":{"stackTrace":"","statusValue":"INFO"},"type":"MESSAGE","name":"","message":"Variable \u0027var_lastName\u0027 is set to Gituto","startTime":1512465529691,"endTime":0,"childRecords":[],"interuppted":false},{"testStatus":{"stackTrace":"","statusValue":"INFO"},"type":"MESSAGE","name":"","message":"Variable \u0027var_email\u0027 is set to dennisgituto@yahoo.com","startTime":1512465529692,"endTime":0,"childRecords":[],"interuppted":false},{"testStatus":{"stackTrace":"","statusValue":"INFO"},"type":"MESSAGE","name":"","message":"Variable \u0027var_password\u0027 is set to desteg","startTime":1512465529693,"endTime":0,"childRecords":[],"interuppted":false},{"testStatus":{"stackTrace":"","statusValue":"INFO"},"type":"MESSAGE","name":"","message":"Variable \u0027var_confirmPassword\u0027 is set to desteg","startTime":1512465529694,"endTime":0,"childRecords":[],"interuppted":false},{"index":1,"isIgnoredIfFailed":false,"type":"TEST_STEP","name":"callTestCase","message":"Call Test Case \u0027Test Cases/Request A Meeting/Request a Meeting Menu\u0027 successfully","description":"","startTime":1512465530142,"endTime":1512465584319,"childRecords":[{"isOptional":false,"type":"TEST_CASE","name":"Test Cases/Request A Meeting/Request a Meeting Menu","id":"Test Cases/Request A Meeting/Request a Meeting Menu","source":"C:\\\\Users\\\\Dennis Gituto\\\\git\\\\VSMS-Test-AutomationTest Cases\\\\Request A Meeting\\\\Request a Meeting Menu.tc","message":"Test Cases/Request A Meeting/Request a Meeting Menu","description":"Contains all the common steps in Request Meeting","startTime":1512465531117,"endTime":1512465584290,"childRecords":[{"testStatus":{"stackTrace":"","statusValue":"INFO"},"type":"MESSAGE","name":"","message":"Evaluating variables for test case","startTime":1512465531134,"endTime":0,"childRecords":[],"interuppted":false},{"testStatus":{"stackTrace":"","statusValue":"INFO"},"type":"MESSAGE","name":"","message":"Variable \u0027var_url\u0027 is set to https://sandbox.vsms.tezzasolutions.com/index","startTime":1512465531135,"endTime":0,"childRecords":[],"interuppted":false},{"index":1,"isIgnoredIfFailed":false,"type":"TEST_STEP","name":"openBrowser","message":"Browser is opened with url: \u0027\u0027","description":"","startTime":1512465531311,"endTime":1512465534472,"childRecords":[{"testStatus":{"stackTrace":"","statusValue":"PASSED"},"type":"MESSAGE","name":"","message":"Browser is opened with url: \u0027\u0027","startTime":1512465534471,"endTime":0,"childRecords":[],"interuppted":false}],"interuppted":false},{"index":2,"isIgnoredIfFailed":false,"type":"TEST_STEP","name":"navigateToUrl","message":"Navigate to \u0027https://sandbox.vsms.tezzasolutions.com/index\u0027 successfully","description":"","startTime":1512465534472,"endTime":1512465577860,"childRecords":[{"testStatus":{"stackTrace":"","statusValue":"PASSED"},"type":"MESSAGE","name":"","message":"Navigate to \u0027https://sandbox.vsms.tezzasolutions.com/index\u0027 successfully","startTime":1512465577858,"endTime":0,"childRecords":[],"interuppted":false}],"interuppted":false},{"index":3,"isIgnoredIfFailed":false,"type":"TEST_STEP","name":"maximizeWindow","message":"Current window maximized","description":"","startTime":1512465577861,"endTime":1512465579051,"childRecords":[{"testStatus":{"stackTrace":"","statusValue":"PASSED"},"type":"MESSAGE","name":"","message":"Current window maximized","startTime":1512465579051,"endTime":0,"childRecords":[],"interuppted":false}],"interuppted":false},{"index":4,"isIgnoredIfFailed":false,"type":"TEST_STEP","name":"click","message":"Object: \u0027Object Repository/Request A meeting/Request meeting Page/button_REQUEST A MEETING\u0027 is clicked on","description":"","startTime":1512465579052,"endTime":1512465579274,"childRecords":[{"testStatus":{"stackTrace":"","statusValue":"PASSED"},"type":"MESSAGE","name":"","message":"Object: \u0027Object Repository/Request A meeting/Request meeting Page/button_REQUEST A MEETING\u0027 is clicked on","startTime":1512465579274,"endTime":0,"childRecords":[],"interuppted":false}],"interuppted":false},{"index":5,"isIgnoredIfFailed":false,"type":"TEST_STEP","name":"delay","message":"Delayed 5 second(s)","description":"","startTime":1512465579275,"endTime":1512465584288,"childRecords":[{"testStatus":{"stackTrace":"","statusValue":"PASSED"},"type":"MESSAGE","name":"","message":"Delayed 5 second(s)","startTime":1512465584286,"endTime":0,"childRecords":[],"interuppted":false}],"interuppted":false},{"testStatus":{"stackTrace":"","statusValue":"PASSED"},"type":"MESSAGE","name":"","message":"Test Cases/Request A Meeting/Request a Meeting Menu","startTime":1512465584289,"endTime":0,"childRecords":[],"interuppted":false}],"interuppted":false},{"testStatus":{"stackTrace":"","statusValue":"PASSED"},"type":"MESSAGE","name":"","message":"Call Test Case \u0027Test Cases/Request A Meeting/Request a Meeting Menu\u0027 successfully","startTime":1512465584312,"endTime":0,"childRecords":[],"interuppted":false}],"interuppted":false},{"index":2,"isIgnoredIfFailed":false,"type":"TEST_STEP","name":"setText","message":"Text \u0027Mr\u0027 is set on object \u0027Object Repository/Request A meeting/Sign Up In Request Meeting/input_title\u0027","description":"","startTime":1512465584321,"endTime":1512465584652,"childRecords":[{"testStatus":{"stackTrace":"","statusValue":"PASSED"},"type":"MESSAGE","name":"","message":"Text \u0027Mr\u0027 is set on object \u0027Object Repository/Request A meeting/Sign Up In Request Meeting/input_title\u0027","startTime":1512465584652,"endTime":0,"childRecords":[],"interuppted":false}],"interuppted":false},{"index":3,"isIgnoredIfFailed":false,"type":"TEST_STEP","name":"setText","message":"Text \u0027Dennis\u0027 is set on object \u0027Object Repository/Request A meeting/Sign Up In Request Meeting/input_firstname\u0027","description":"","startTime":1512465584653,"endTime":1512465584898,"childRecords":[{"testStatus":{"stackTrace":"","statusValue":"PASSED"},"type":"MESSAGE","name":"","message":"Text \u0027Dennis\u0027 is set on object \u0027Object Repository/Request A meeting/Sign Up In Request Meeting/input_firstname\u0027","startTime":1512465584898,"endTime":0,"childRecords":[],"interuppted":false}],"interuppted":false},{"index":4,"isIgnoredIfFailed":false,"type":"TEST_STEP","name":"setText","message":"Text \u0027Gituto\u0027 is set on object \u0027Object Repository/Request A meeting/Sign Up In Request Meeting/input_lastname\u0027","description":"","startTime":1512465584899,"endTime":1512465585214,"childRecords":[{"testStatus":{"stackTrace":"","statusValue":"PASSED"},"type":"MESSAGE","name":"","message":"Text \u0027Gituto\u0027 is set on object \u0027Object Repository/Request A meeting/Sign Up In Request Meeting/input_lastname\u0027","startTime":1512465585213,"endTime":0,"childRecords":[],"interuppted":false}],"interuppted":false},{"index":5,"isIgnoredIfFailed":false,"type":"TEST_STEP","name":"selectOptionByValue","message":"All options with value \u002714\u0027 are selected in object \u0027Object Repository/Request A meeting/Sign Up In Request Meeting/select_tenant_id\u0027 ","description":"","startTime":1512465585214,"endTime":1512465585405,"childRecords":[{"testStatus":{"stackTrace":"","statusValue":"PASSED"},"type":"MESSAGE","name":"","message":"All options with value \u002714\u0027 are selected in object \u0027Object Repository/Request A meeting/Sign Up In Request Meeting/select_tenant_id\u0027 ","startTime":1512465585405,"endTime":0,"childRecords":[],"interuppted":false}],"interuppted":false},{"index":6,"isIgnoredIfFailed":false,"type":"TEST_STEP","name":"setText","message":"Text \u0027dennisgituto@yahoo.com\u0027 is set on object \u0027Object Repository/Request A meeting/Sign Up In Request Meeting/input_email\u0027","description":"","startTime":1512465585406,"endTime":1512465585961,"childRecords":[{"testStatus":{"stackTrace":"","statusValue":"PASSED"},"type":"MESSAGE","name":"","message":"Text \u0027dennisgituto@yahoo.com\u0027 is set on object \u0027Object Repository/Request A meeting/Sign Up In Request Meeting/input_email\u0027","startTime":1512465585961,"endTime":0,"childRecords":[],"interuppted":false}],"interuppted":false},{"index":7,"isIgnoredIfFailed":false,"type":"TEST_STEP","name":"setText","message":"Text \u0027desteg\u0027 is set on object \u0027Object Repository/Request A meeting/Sign Up In Request Meeting/input_password\u0027","description":"","startTime":1512465585962,"endTime":1512465586245,"childRecords":[{"testStatus":{"stackTrace":"","statusValue":"PASSED"},"type":"MESSAGE","name":"","message":"Text \u0027desteg\u0027 is set on object \u0027Object Repository/Request A meeting/Sign Up In Request Meeting/input_password\u0027","startTime":1512465586244,"endTime":0,"childRecords":[],"interuppted":false}],"interuppted":false},{"index":8,"isIgnoredIfFailed":false,"type":"TEST_STEP","name":"setText","message":"Text \u0027var_confirmPassword\u0027 is set on object \u0027Object Repository/Request A meeting/Sign Up In Request Meeting/input_password_confirmation\u0027","description":"","startTime":1512465586245,"endTime":1512465586709,"childRecords":[{"testStatus":{"stackTrace":"","statusValue":"PASSED"},"type":"MESSAGE","name":"","message":"Text \u0027var_confirmPassword\u0027 is set on object \u0027Object Repository/Request A meeting/Sign Up In Request Meeting/input_password_confirmation\u0027","startTime":1512465586707,"endTime":0,"childRecords":[],"interuppted":false}],"interuppted":false},{"index":9,"isIgnoredIfFailed":false,"type":"TEST_STEP","name":"click","message":"Object: \u0027Object Repository/Request A meeting/Sign Up In Request Meeting/button_Sign Up\u0027 is clicked on","description":"","startTime":1512465586710,"endTime":1512465586832,"childRecords":[{"testStatus":{"stackTrace":"","statusValue":"PASSED"},"type":"MESSAGE","name":"","message":"Object: \u0027Object Repository/Request A meeting/Sign Up In Request Meeting/button_Sign Up\u0027 is clicked on","startTime":1512465586832,"endTime":0,"childRecords":[],"interuppted":false}],"interuppted":false},{"index":10,"isIgnoredIfFailed":false,"type":"TEST_STEP","name":"delay","message":"Delayed 2 second(s)","description":"","startTime":1512465586833,"endTime":1512465588837,"childRecords":[{"testStatus":{"stackTrace":"","statusValue":"PASSED"},"type":"MESSAGE","name":"","message":"Delayed 2 second(s)","startTime":1512465588834,"endTime":0,"childRecords":[],"interuppted":false}],"interuppted":false},{"index":11,"isIgnoredIfFailed":false,"type":"TEST_STEP","name":"verifyElementVisible","message":"Object \u0027Object Repository/Request A meeting/Sign Up In Request Meeting/Verify Sign Up in Request Meeting/Request Sign up\u0027 is visible","description":"","startTime":1512465588838,"endTime":1512465588968,"childRecords":[{"testStatus":{"stackTrace":"","statusValue":"PASSED"},"type":"MESSAGE","name":"","message":"Object \u0027Object Repository/Request A meeting/Sign Up In Request Meeting/Verify Sign Up in Request Meeting/Request Sign up\u0027 is visible","startTime":1512465588967,"endTime":0,"childRecords":[],"interuppted":false}],"interuppted":false},{"index":12,"isIgnoredIfFailed":false,"type":"TEST_STEP","name":"delay","message":"Delayed 3 second(s)","description":"","startTime":1512465588969,"endTime":1512465591971,"childRecords":[{"testStatus":{"stackTrace":"","statusValue":"PASSED"},"type":"MESSAGE","name":"","message":"Delayed 3 second(s)","startTime":1512465591970,"endTime":0,"childRecords":[],"interuppted":false}],"interuppted":false},{"index":13,"isIgnoredIfFailed":false,"type":"TEST_STEP","name":"closeBrowser","message":"Browser is closed","description":"","startTime":1512465591973,"endTime":1512465592766,"childRecords":[{"testStatus":{"stackTrace":"","statusValue":"PASSED"},"type":"MESSAGE","name":"","message":"Browser is closed","startTime":1512465592765,"endTime":0,"childRecords":[],"interuppted":false}],"interuppted":false},{"testStatus":{"stackTrace":"","statusValue":"PASSED"},"type":"MESSAGE","name":"","message":"Test Cases/Request A Meeting/Sign Up in Request Meeting","startTime":1512465592768,"endTime":0,"childRecords":[],"interuppted":false}],"interuppted":false}],"interuppted":false}